aliyun_controller/__init__.py
aliyun_controller/config.yaml.example
aliyun_controller/main.py
aliyun_controller/modules/__init__.py
aliyun_controller/modules/billing.py
aliyun_controller/modules/dns.py
aliyun_controller-0.1.2.dist-info/METADATA
aliyun_controller-0.1.2.dist-info/WHEEL
aliyun_controller-0.1.2.dist-info/entry_points.txt
aliyun_controller-0.1.2.dist-info/top_level.txt
aliyun_controller-0.1.2.dist-info/RECORD
