Metadata-Version: 2.4
Name: aliyun_controller
Version: 0.1.2
Summary: A command-line tool for managing Alibaba Cloud services including billing queries and DNS management
Author-email: Moha-Master <hongkongreporter@outlook.com>
License-Expression: MIT
Project-URL: Homepage, https://github.com/Moha-Master/Aliyun-Controller
Project-URL: Repository, https://github.com/Moha-Master/Aliyun-Controller
Project-URL: Issues, https://github.com/Moha-Master/Aliyun-Controller/issues
Classifier: Development Status :: 4 - Beta
Classifier: Intended Audience :: Developers
Classifier: Programming Language :: Python :: 3
Classifier: Programming Language :: Python :: 3.8
Classifier: Programming Language :: Python :: 3.9
Classifier: Programming Language :: Python :: 3.10
Classifier: Programming Language :: Python :: 3.11
Classifier: Programming Language :: Python :: 3.12
Requires-Python: >=3.8
Requires-Dist: alibabacloud-ecs20140526
Requires-Dist: alibabacloud-bssopenapi20171214
Requires-Dist: alibabacloud-alidns20150109
Requires-Dist: InquirerPy
Requires-Dist: PyYAML
Provides-Extra: dev
Requires-Dist: pytest>=6.0; extra == "dev"
Requires-Dist: pytest-cov; extra == "dev"
